Metadata-Version: 2.4
Name: ckanext-auth
Version: 0.3.2
Summary: 2FA authentication for CKAN
Author-email: DataShades <datashades@linkdigital.com.au>, Oleksandr Cherniavskyi <mutantsan@gmail.com>
Maintainer-email: DataShades <datashades@linkdigital.com.au>
License: AGPL
Project-URL: Homepage, https://github.com/DataShades/ckanext-auth
Keywords: CKAN
Classifier: Development Status :: 4 - Beta
Classifier: License :: OSI Approved :: GNU Affero General Public License v3 or later (AGPLv3+)
Classifier: Programming Language :: Python :: 3.8
Classifier: Programming Language :: Python :: 3.9
Classifier: Programming Language :: Python :: 3.10
License-File: LICENSE
Dynamic: license-file
